mips/single_cycle/data_mem_64x32.v
`timescale 1ns/1ns

/*
	synchronous read and write memory unit
 */

module data_mem_64x32(clk, addr, rd, wd, memwrite, memread);

	/*
	 *	reg addr must be long enough to address the entire memory
	 */

	input clk;
	input [5:0] addr;
	output wire [31:0] rd;
	input [31:0] wd;
	input memwrite;
	input memread;

	reg [31:0] memory [0:63];

	integer i;

	initial begin
		for(i = 0; i < 64; i = i + 1)
			memory[i] <= i;
	end


	// data is not available until the next clock cycle
	always @(posedge clk) begin
		if (memwrite == 1'b1)
			memory[addr] <= wd;
	end

	assign rd = (memread == 1'b1) ? memory[addr] : 32'bX;

endmodule

mips/pipeline/alu.v
`timescale 1ns/1ps

/*
	32 bit mips alu
	no cout?
	signed/unsigned ops?
 */

module alu(alucont, rd1, rd2, res, zero);
	input [3:0] alucont;
	input [31:0] rd1;
	input [31:0] rd2;
	output reg [31:0] res;
	output wire zero;

	localparam AND 	= 4'b0000;
	localparam OR 	= 4'b0001;
	localparam ADD 	= 4'b0010;
	localparam SUB 	= 4'b0110;
	localparam SLT 	= 4'b0111;
	localparam NOR 	= 4'b1100;

	always @(*) begin
		case(alucont)
			AND		: begin
				res <= rd1 & rd2;
			end
			OR 		: begin
				res <= rd1 | rd2;
			end
			ADD 	: begin
				res <= rd1 + rd2;
			end
			SUB 	: begin
				res <= rd1 - rd2;
			end
			SLT 	: begin
				res <= (rd1 < rd2) ? 1 : 0;
			end
			NOR 	: begin
				res <= ~(rd1 | rd2);
			end
		endcase
	end

	// bitwise or on all the bits in the bus
	assign zero = ~(|res);

endmodule

mips/single_cycle/sign_ext_16_32.v
`timescale 1 ns / 100 ps

/*
	16 to 32 bit sign extender
*/

module sign_ext_16_32(d, q);
	input [15:0] d;
	output [31:0] q;

	assign q = { {16{d[15]}}, d};

endmodule

mips/single_cycle/register_file.v
`timescale 1 ns / 100 ps

/*
	register file implemented based on the description 
	provided in Computer Organization and Design, 5th
*/

module register_file(clk, ra1, ra2, wa, wd, rd1, rd2, regwrite);
	input clk;
	input [4:0] ra1;
	input [4:0] ra2;
	input [4:0] wa;
	input [31:0] wd;
	output wire [31:0] rd1;
	output wire [31:0] rd2;
	input regwrite;

	// 32 element array of 32 bit wide registers
	reg [31:0] reg_file [0:31];

	integer i;

	initial begin
		for(i = 0; i < 32; i = i + 1)
			reg_file[i] = i;
	end

	assign rd1 = reg_file[ra1];
	assign rd2 = reg_file[ra2];

	always @(posedge clk) 
	begin
		if(regwrite)
			reg_file[wa] <= wd;	
	end

endmodule

mips/pipeline/inst_mem_64x32.v
`timescale 1ns/1ns

/*
	holds preloaded program, is addressed by the program counter
*/

module inst_mem_64x32(ra, rd);
	input [5:0] ra;
	output [31:0] rd;

	reg [31:0] memory [0:63];

	assign rd = memory[ra];

	integer i;

endmodule

mips/single_cycle/main.v
`timescale 1ns/1ns

/*
	single cycle mips implementation

	Supported instructions:
		BEQ
		SUB
		ADD
		OR
		SLT
		NOR
		AND
		LW
		SW

	R-Type
	    OP      RS      RT      RD    SHAMT FUNCT
	|-------|-------|-------|-------|------|-----|
	  31:26   25:21   20:16   15:11   10:6   5:0

	LW/SW
	    OP      RS      RT         ADDRESS
	|-------|-------|-------|--------------------|
	  31:26   25:21   20:16         15:0

	Branch
        OP      RS      RT         ADDRESS
	|-------|-------|-------|--------------------|
	  31:26   25:21   20:16         15:0

	Jump
        OP               ADDRESS
	|-------|------------------------------------|
	  31:26               25:0


	Need resets for the modules
 */

module single_cycle_mips_32(clk, rst);
	input clk;
	input rst;

	///////////////////////////////////////////////////////////////////////////
	//
	//	Control Lines
	//	
	//	Control module for control lines, maps instruction[31:26] to lines
	//
	///////////////////////////////////////////////////////////////////////////

	localparam R_TYPE 		= 6'b000000;
	localparam LOAD_WORD 	= 6'b100011;
	localparam STORE_WORD 	= 6'b101011;
	localparam BRANCH_EQ	= 6'b000100;
	localparam JUMP 		= 6'b000010;

	reg RegDst;
	reg Branch;
	reg MemRead;
	reg MemToReg;
	reg [1:0] AluOP;
	reg MemWrite;
	reg ALUSrc;
	reg RegWrite;
	reg Jump;

	wire [31:0] instruction;

	initial RegDst = 1'b0;
	initial Branch = 1'b0;
	initial MemRead = 1'b0;
	initial MemToReg = 1'b0;
	initial AluOP = 2'b00;
	initial MemWrite = 1'b0;
	initial ALUSrc = 1'b0;
	initial RegWrite = 1'b0;
	initial Jump = 1'b0;

	always @(*) begin
		case(instruction[31:26])
			R_TYPE 	: begin
				// R type uses both data addresses and a result address
				RegDst <= 1'b1;
				// second data reg goes to alu
				ALUSrc <= 1'b0;
				// alu result is sent back to the register file
				MemToReg <= 1'b0;
				// writing data bact to register file
				RegWrite <= 1'b1;
				// not reading from memory
				MemRead <= 1'b0;
				// not reading to memory
				MemWrite <= 1'b0;
				// increment PC;
				Branch <= 1'b0;
				// aluop 10 is R-type
				AluOP <= 2'b10;
				// not jump
				Jump <= 1'b0;
			end
			LOAD_WORD 	: begin
				// writing mem data back to register file 
				RegDst <= 1'b0;
				// send the immediate value to the alu for addres offset
				ALUSrc <= 1'b1;
				// send RAM memory to register
				MemToReg <= 1'b1;
				// writing to register
				RegWrite <= 1'b1;
				// reading from memory
				MemRead <= 1'b1;
				// prevent memory corruption
				MemWrite <= 1'b0;
				// increment PC
				Branch <= 1'b0;
				// add address and immediate
				AluOP <= 2'b00;
				// not jump
				Jump <= 1'b0;
			end
			STORE_WORD 	: begin
				// second data field not used
				RegDst <= 1'bX;
				// send immediate field to alu
				ALUSrc <= 1'b1;
				// not writing data back to register
				MemToReg <= 1'bX;
				// prevent register corruption
				RegWrite <= 1'b0;
				// prevent RAM corruption, this might not matter
				MemRead <= 1'b0;
				// write data to appropriate address
				MemWrite <= 1'b1; 
				// increment pc
				Branch <= 1'b0;
				// calculate address from immediate and PC+4
				AluOP <= 2'b00;
				// not jump
				Jump <= 1'b0;
			end
			BRANCH_EQ 	: begin
				// no third field necessary
				RegDst <= 1'bX;
				// send second data field to alu
				ALUSrc <= 1'b0;
				// not writing back from memory to register
				MemToReg <= 1'bX;
				// not writing to register, prevent corruption
				RegWrite <= 1'b0;
				// not reading from register
				MemRead <= 1'b0;
				// not writing to memory
				MemWrite <= 1'b0;
				// branch if zero
				Branch = 1'b1;
				// check if zero subtract
				AluOP <= 2'b01;
				// not jump
				Jump <= 1'b0;
			end
			JUMP 	: begin
				// no third field necessary
				RegDst <= 1'bX;
				// path not used in jump
				ALUSrc <= 1'bX;
				// not writing back from memory to register
				MemToReg <= 1'bX;
				// not writing to register, prevent corruption
				RegWrite <= 1'b0;
				// not reading from register
				MemRead <= 1'bX;
				// not writing to memory, prevent corruption
				MemWrite <= 1'b0;
				// branch if zero
				Branch = 1'bX;
				// check if zero subtract
				AluOP <= 2'bX;
				// jump!
				Jump <= 1'b1;
			end
			default begin
				
			end
		endcase
	end

	///////////////////////////////////////////////////////////////////////////
	//
	//	PC
	//	There are 64 instruction memory locations, log2(64) = 6 address bits
	//	and then there are 4 byte locations inside each 32 bit address
	//		---> 8 address bits needed, 32 given, possibe address space: 4G
	///////////////////////////////////////////////////////////////////////////

	wire [31:0] next_instruction;
	reg [31:0] program_counter;
	reg pc_init;

	initial pc_init = 1'b0;
	initial program_counter = 32'b0;

	// assign next_instruction after address calculation modules
	// and also save logic for reset and first instruction
	always @(posedge clk or posedge rst) begin
		if (rst) begin
			// reset precedence
			program_counter <= 32'bX;
		end
		else begin
			if(~pc_init) begin
				program_counter <= 32'b0;
				pc_init <= 1'b1;
			end
			else begin
				program_counter <= next_instruction;	
			end
		end
	end

	wire [31:0] program_counter_plus_4;
	assign program_counter_plus_4 = program_counter + 4;

	///////////////////////////////////////////////////////////////////////////
	//
	//	Instruction Memory
	//	Needs to be loaded before execution
	//
	//
	///////////////////////////////////////////////////////////////////////////	

	inst_mem_64x32 inst_mem(
		.ra(program_counter[7:2]),
		.rd(instruction)
		);

	///////////////////////////////////////////////////////////////////////////
	//
	//	Register File
	//	
	//
	//
	///////////////////////////////////////////////////////////////////////////

	wire [4:0] write_address;
	assign write_address = RegDst ? instruction[15:11] : instruction[20:16];

	// assign write data after mem access
	wire [31:0] write_data;
	wire [31:0] read_data_1;
	wire [31:0] read_data_2;

	register_file reg_file(
		.clk(clk),
		.ra1(instruction[25:21]),
		.ra2(instruction[20:16]),
		.wa(write_address),
		.wd(write_data),
		.rd1(read_data_1),
		.rd2(read_data_2),
		.regwrite(RegWrite)
		);

	///////////////////////////////////////////////////////////////////////////
	//
	//	Sign Extender
	//	
	//
	//
	///////////////////////////////////////////////////////////////////////////

	wire [31:0] sign_extended_immediate_16;

	sign_ext_16_32 sign_ext(
		.d(instruction[15:0]),
		.q(sign_extended_immediate_16)
		);

	///////////////////////////////////////////////////////////////////////////
	//
	//	ALU
	//	
	//	Need ALU control unit, takes in AluOP and funct field
	//	and outputs the alu control lines
	///////////////////////////////////////////////////////////////////////////	

	reg [3:0] alu_control;
	initial alu_control = 0;

	localparam AND 	= 4'b0000;
	localparam OR 	= 4'b0001;
	localparam ADD 	= 4'b0010;
	localparam SUB 	= 4'b0110;
	localparam SLT 	= 4'b0111;
	localparam NOR 	= 4'b1100;

	wire [5:0] funct_control;
	assign funct_control = instruction[5:0];

	always @(*) begin

		// default add (LW and SW)
		if (~AluOP[1] && ~AluOP[0]) begin
			alu_control <= ADD;
		end

		// default sub (beq)
		else if (AluOP[0]) begin
			alu_control <= SUB;
		end

		// r-type
		else if(AluOP[1]) begin
			if(funct_control[3:0] == 4'b0000)
				alu_control <= ADD;
			else if(funct_control[3:0] == 4'b0010)
				alu_control <= SUB;
			else if(funct_control[3:0] == 4'b0100)
				alu_control <= AND;
			else if(funct_control[3:0] == 4'b0101)
				alu_control <= OR;
			else if(funct_control[3:0] == 4'b1010)
				alu_control <= SLT;
			else if(funct_control[3:0] == 4'b0111)
				alu_control <= NOR;
			else
				alu_control <= 4'bXXXX;
		end
		else
			alu_control <= 4'bXXXX;
	end

	wire [31:0] alu_input_1;
	wire [31:0] alu_input_2;
	wire [31:0] alu_result;
	wire alu_zero;

	assign alu_input_1 = read_data_1;
	assign alu_input_2 = ALUSrc ? sign_extended_immediate_16 : read_data_2;

	alu alu(
		.alucont(alu_control),
		.rd1(alu_input_1),
		.rd2(alu_input_2),
		.res(alu_result),
		.zero(alu_zero)
		);

	///////////////////////////////////////////////////////////////////////////
	//
	//	Address Calculation
	//	
	//	
	//	
	///////////////////////////////////////////////////////////////////////////	

	wire [31:0] address_calc;
	wire [31:0] immediate_shift_left_2;
	wire PCSrc;
	wire [31:0] pre_jump_inst;
	wire [31:0] jump_address;

	assign jump_address = {program_counter_plus_4[31:28], instruction[25:0], 2'b0};
	assign PCSrc = Branch & alu_zero;
	assign immediate_shift_left_2 = {sign_extended_immediate_16[29:0], 2'b0};
	assign address_calc = program_counter_plus_4 + immediate_shift_left_2;
	assign pre_jump_inst = PCSrc ? address_calc : program_counter_plus_4;
	assign next_instruction = Jump ? jump_address : pre_jump_inst;

	///////////////////////////////////////////////////////////////////////////
	//
	//	Data Memory
	//	
	//	RAM
	//	
	///////////////////////////////////////////////////////////////////////////

	wire [31:0] data_mem_data;

	// lower 6 address bits are focused on because of the address size
	data_mem_64x32 data_mem(
		.clk(clk),
		.addr(alu_result[5:0]),
		.rd(data_mem_data),
		.wd(read_data_2),
		.memwrite(MemWrite),
		.memread(MemRead)
		);

	assign write_data = MemToReg ? data_mem_data : alu_result;

endmodule

mips/pipeline/single_cycle_tb.v
`timescale 1ns/1ns

/*
	R-Type
	    OP      RS      RT      RD    SHAMT  FUNCT
	|-------|-------|-------|-------|------|------|
	  31:26   25:21   20:16   15:11   10:6   5:0

	LW/SW
	    OP      RS      RT         ADDRESS
	|-------|-------|-------|---------------------|
	  31:26   25:21   20:16         15:0
	
	Branch
        OP      RS      RT         ADDRESS
	|-------|-------|-------|---------------------|
	  31:26   25:21   20:16         15:0

	Jump
        OP               ADDRESS
	|-------|------------------------------------|
	  31:26               25:0


	LW $(RT) OFFSET+$(RS)
	SW $(RT) OFFSET+$(RS)


	Note: data mem and reg file are loaded with natural values initially
			inst mem is uninitialized
 */

module test_bench#(
	parameter CLK_PERIOD = 10 //ns
	);

	reg rst_tb = 1;
	
	reg clk_tb = 1;

	// 100Mhz clock
	always #(CLK_PERIOD/2) clk_tb = ~clk_tb;

	///////////////////////////////////////////////////////////////////////////
	//
	// 
	//	Instantiations
	//
	//
	///////////////////////////////////////////////////////////////////////////

	single_cycle_mips_32 UUT(
		.clk(clk_tb),
		.rst(rst_tb)
		);

	///////////////////////////////////////////////////////////////////////////
	//
	// 
	//	Initializations
	//
	//
	///////////////////////////////////////////////////////////////////////////

	initial begin
		$dumpfile("simulation.vcd");
		$dumpvars(0, test_bench);
	end

	integer i;

	// load data memory with values
	initial begin
		for(i = 0; i < 64; i = i + 1) begin
			UUT.data_mem.memory[i] = i;
		end
	end

	localparam R_TYPE 		= 6'b000000;
	localparam LOAD_WORD 	= 6'b100011;
	localparam STORE_WORD 	= 6'b101011;
	localparam BRANCH_EQ	= 6'b000100;
	localparam JUMP 		= 6'b000010;

	// function field NOT ALUOP
	localparam AND 			= 6'b100100;
	localparam OR 			= 6'b100101;
	localparam ADD 			= 6'b100000;
	localparam SUB 			= 6'b100010;
	localparam SLT 			= 6'b101010;
	localparam NOR 			= 6'b100111;

	///////////////////////////////////////////////////////////////////////////
	//
	// 
	//	Test Routine
	//
	//
	///////////////////////////////////////////////////////////////////////////

	task dump_data;
		integer i;
		for(i = 0; i < 32; i = i + 1) begin
			$display("UUT address: %d, reg_file data: %d, data_mem data: %d", 
				i, UUT.reg_file.memory[i], UUT.data_mem.memory[i]);
		end
	endtask

	// program
	initial begin

		// wait 2 clocks
		#(2*CLK_PERIOD);
		rst_tb = 1'b0;

		// Dont forget R-Type shamt! 5'b0
		// ADD
		UUT.inst_mem.memory[0] = {LOAD_WORD, 5'd31, 5'd1, 16'd0};
		UUT.inst_mem.memory[1] = {LOAD_WORD, 5'd31, 5'd2, 16'd0};
		UUT.inst_mem.memory[2] = {R_TYPE, 5'd1, 5'd2, 5'd3, 5'b0, ADD};
		UUT.inst_mem.memory[3] = {STORE_WORD, 5'd0, 5'd3, 16'd0};

		// SUB
		UUT.inst_mem.memory[4] = {LOAD_WORD, 5'd31, 5'd1, 16'd0};
		UUT.inst_mem.memory[5] = {LOAD_WORD, 5'd30, 5'd2, 16'd0};
		UUT.inst_mem.memory[6] = {R_TYPE, 5'd1, 5'd2, 5'd3, 5'b0, SUB};
		UUT.inst_mem.memory[7] = {STORE_WORD, 5'd0, 5'd3, 16'd0};

		// OR
		UUT.inst_mem.memory[8] = {LOAD_WORD, 5'd0, 5'd1, 16'd25};
		UUT.inst_mem.memory[9] = {LOAD_WORD, 5'd0, 5'd2, 16'd16};
		UUT.inst_mem.memory[10] = {R_TYPE, 5'd1, 5'd2, 5'd3, 5'b0, OR};
		UUT.inst_mem.memory[11] = {STORE_WORD, 5'd0, 5'd3, 16'd14};

		//AND
		UUT.inst_mem.memory[12] = {LOAD_WORD, 5'd0, 5'd1, 16'd22};
		UUT.inst_mem.memory[13] = {LOAD_WORD, 5'd0, 5'd2, 16'd12};
		UUT.inst_mem.memory[14] = {R_TYPE, 5'd1, 5'd2, 5'd3, 5'b0, AND};
		UUT.inst_mem.memory[15] = {STORE_WORD, 5'd0, 5'd3, 16'd14};

		//SLT
		UUT.inst_mem.memory[16] = {LOAD_WORD, 5'd0, 5'd1, 16'd4};
		UUT.inst_mem.memory[17] = {LOAD_WORD, 5'd0, 5'd2, 16'd5};
		UUT.inst_mem.memory[18] = {R_TYPE, 5'd1, 5'd2, 5'd3, 5'b0, SLT};
		UUT.inst_mem.memory[19] = {STORE_WORD, 5'd0, 5'd3, 16'd14};

		// NOR
		UUT.inst_mem.memory[20] = {LOAD_WORD, 5'd0, 5'd1, 16'd22};
		UUT.inst_mem.memory[21] = {LOAD_WORD, 5'd0, 5'd2, 16'd12};
		UUT.inst_mem.memory[22] = {R_TYPE, 5'd1, 5'd2, 5'd3, 5'b0, NOR};
		UUT.inst_mem.memory[23] = {STORE_WORD, 5'd14, 5'd3, 16'd0};

		// J
		UUT.inst_mem.memory[24] = {JUMP, 26'd26};
		UUT.inst_mem.memory[25] = 32'bX;

		// BEQ, can accept a negative offset, 2's compliment is kinda sick
		UUT.inst_mem.memory[26] = {LOAD_WORD, 5'd0, 5'd1, 16'd5};
		UUT.inst_mem.memory[27] = {LOAD_WORD, 5'd0, 5'd2, 16'd5};
		UUT.inst_mem.memory[28] = {BRANCH_EQ, 5'd1, 5'd2, -16'd29};


		///////////////////////////////////////////////////////////////////////
		//
		//	ADD test
		//
		///////////////////////////////////////////////////////////////////////

		$display("test_bench: running test: ADD");
		// LW $1 0($31)
		#CLK_PERIOD;
		// LW $2 0($31)
		#CLK_PERIOD;
		// ADD $2, $2, $1
		#CLK_PERIOD;
		// SW $2 0($0)
		#CLK_PERIOD;

		// need to wait a little after the next clock cycle to read accurately
		// delta T!
		#1;
		if(UUT.data_mem.memory[0] != (UUT.reg_file.memory[1] + 
			UUT.reg_file.memory[2]))
			$display("test_bench: ADD failure", UUT.reg_file.memory[0],
				UUT.reg_file.memory[1], UUT.reg_file.memory[2]);
		else
			$display("test_bench: ADD succuess");

		//dump_data();

		///////////////////////////////////////////////////////////////////////
		//
		//	SUB test
		//
		///////////////////////////////////////////////////////////////////////

		$display("test_bench: running test: SUB");
		// LW $1 0($31)
		#(CLK_PERIOD - 1);
		// LW $2 30($0)
		#CLK_PERIOD;
		// SUB $3, $1, $2
		#CLK_PERIOD;
		// SW $3 0($0)
		#CLK_PERIOD;

		// need to wait a little after the next clock cycle to read accurately,
		// delta T!
		#1;
		if(UUT.data_mem.memory[0] != (UUT.reg_file.memory[1] - 
			UUT.reg_file.memory[2]))
			$display("test_bench: SUB failure");
		else
			$display("test_bench: SUB succuess");

		//dump_data();

		///////////////////////////////////////////////////////////////////////
		//
		//	OR test
		//
		///////////////////////////////////////////////////////////////////////

		// LW $1 25($0)
		#(CLK_PERIOD-1);
		// LW $2 16($0)
		#CLK_PERIOD;
		// OR $3, $1, $2
		#CLK_PERIOD;
		// SW $3 14($0)
		#CLK_PERIOD;

		$display("test_bench: running test: OR");

		#1;
		if(UUT.data_mem.memory[14] != (UUT.reg_file.memory[1] | 
			UUT.reg_file.memory[2]))
			$display("test_bench: OR failure");
		else
			$display("test_bench: OR succuess");

		//dump_data();

		///////////////////////////////////////////////////////////////////////
		//
		//	AND test
		//
		///////////////////////////////////////////////////////////////////////

		// LW $1 22($0)
		#(CLK_PERIOD-1);
		// LW $2 12($0)
		#CLK_PERIOD;
		// AND $3, $1, $2
		#CLK_PERIOD;
		// SW $3 14($0)
		#CLK_PERIOD;

		$display("test_bench: running test: AND");

		#1;
		if(UUT.data_mem.memory[14] != (UUT.reg_file.memory[1] & 
			UUT.reg_file.memory[2]))
			$display("test_bench: AND failure");
		else
			$display("test_bench: AND succuess");

		//dump_data();

		///////////////////////////////////////////////////////////////////////
		//
		//	SLT test
		//
		///////////////////////////////////////////////////////////////////////

		// LW $1 4($0)
		#(CLK_PERIOD-1);
		// LW $2 5($0)
		#CLK_PERIOD;
		// SLT $3, $1, $2
		#CLK_PERIOD;
		// SW $3 14($0)
		#CLK_PERIOD;

		$display("test_bench: running test: SLT");

		#1;
		if(UUT.data_mem.memory[14] != (UUT.reg_file.memory[1] < 
			UUT.reg_file.memory[2]))
			$display("test_bench: SLT failure");
		else
			$display("test_bench: SLT succuess");

		//dump_data();

		///////////////////////////////////////////////////////////////////////
		//
		//	NOR test
		//
		///////////////////////////////////////////////////////////////////////

		// LW $1 22($0)
		#(CLK_PERIOD-1);
		// LW $2 12($0)
		#CLK_PERIOD;
		// NOR $3, $1, $2
		#CLK_PERIOD;
		// SW $3 14($0)
		#CLK_PERIOD;

		$display("test_bench: running test: NOR");

		#1;
		if(UUT.data_mem.memory[14] != ~(UUT.reg_file.memory[1] | 
			UUT.reg_file.memory[2]))
			$display("test_bench: NOR failure");
		else
			$display("test_bench: NOR succuess");

		//dump_data();

		///////////////////////////////////////////////////////////////////////
		//
		//	JUMP test
		//
		///////////////////////////////////////////////////////////////////////

		// Jump
		#(CLK_PERIOD-1);

		$display("test_bench: running test: J");

		#1;
		if(UUT.program_counter[31:2] != 30'd26)
			$display("test_bench: J failure");
		else
			$display("test_bench: J succuess");

		///////////////////////////////////////////////////////////////////////
		//
		//	BEQ test
		//
		///////////////////////////////////////////////////////////////////////

		// LW $1 5($0)
		#(CLK_PERIOD-1);
		// LW $2 5($0)
		#CLK_PERIOD;
		// BEQ $1, $2, -27
		#CLK_PERIOD;

		$display("test_bench: running test: BEQ");

		#1;
		if(UUT.program_counter != 32'b0)
			$display("test_bench: BEQ failure");
		else
			$display("test_bench: BEQ succuess");

		//dump_data();

		// reserve margin at the end of test
		#(10*CLK_PERIOD);
		$finish;
	end

endmodule

mips/pipeline/simulation.vcd
$date
	Tue Jan  1 16:37:36 2019
$end
$version
	Icarus Verilog
$end
$timescale
	1ps
$end
$scope module test_bench $end
$var reg 1 ! clk_tb $end
$var integer 32 " i [31:0] $end
$var reg 1 # rst_tb $end
$scope module UUT $end
$var wire 1 $ PCSrc $end
$var wire 32 % address_calc [31:0] $end
$var wire 32 & alu_input_1 [31:0] $end
$var wire 32 ' alu_input_2 [31:0] $end
$var wire 32 ( alu_result [31:0] $end
$var wire 1 ) alu_zero $end
$var wire 1 * clk $end
$var wire 32 + data_mem_data [31:0] $end
$var wire 6 , funct_control [5:0] $end
$var wire 32 - immediate_shift_left_2 [31:0] $end
$var wire 32 . instruction [31:0] $end
$var wire 32 / jump_address [31:0] $end
$var wire 32 0 next_instruction [31:0] $end
$var wire 32 1 pre_jump_inst [31:0] $end
$var wire 32 2 program_counter_plus_4 [31:0] $end
$var wire 32 3 read_data_1 [31:0] $end
$var wire 32 4 read_data_2 [31:0] $end
$var wire 1 5 rst $end
$var wire 32 6 sign_extended_immediate_16 [31:0] $end
$var wire 5 7 write_address [4:0] $end
$var wire 32 8 write_data [31:0] $end
$var reg 1 9 ALUSrc $end
$var reg 2 : AluOP [1:0] $end
$var reg 1 ; Branch $end
$var reg 1 < Jump $end
$var reg 1 = MemRead $end
$var reg 1 > MemToReg $end
$var reg 1 ? MemWrite $end
$var reg 1 @ RegDst $end
$var reg 1 A RegWrite $end
$var reg 4 B alu_control [3:0] $end
$var reg 1 C pc_init $end
$var reg 32 D program_counter [31:0] $end
$scope module inst_mem $end
$var wire 6 E ra [5:0] $end
$var wire 32 F rd [31:0] $end
$upscope $end
$scope module reg_file $end
$var wire 1 * clk $end
$var wire 5 G ra1 [4:0] $end
$var wire 5 H ra2 [4:0] $end
$var wire 1 I regwrite $end
$var wire 5 J wa [4:0] $end
$var wire 32 K wd [31:0] $end
$var integer 32 L i [31:0] $end
$var reg 32 M rd1 [31:0] $end
$var reg 32 N rd2 [31:0] $end
$upscope $end
$scope module sign_ext $end
$var wire 16 O d [15:0] $end
$var wire 32 P q [31:0] $end
$upscope $end
$scope module alu $end
$var wire 4 Q alucont [3:0] $end
$var wire 32 R rd1 [31:0] $end
$var wire 32 S rd2 [31:0] $end
$var wire 1 ) zero $end
$var reg 32 T res [31:0] $end
$upscope $end
$scope module data_mem $end
$var wire 6 U addr [5:0] $end
$var wire 1 * clk $end
$var wire 1 V memread $end
$var wire 1 W memwrite $end
$var wire 32 X rd [31:0] $end
$var wire 32 Y wd [31:0] $end
$var integer 32 Z i [31:0] $end
$upscope $end
$upscope $end
$scope task dump_data $end
$var integer 32 [ i [31:0] $end
$upscope $end
$upscope $end
$enddefinitions $end
#0
$dumpvars
bx [
b1000000 Z
bx Y
bx X
0W
0V
bx U
bx T
bx S
bx R
b10 Q
bx P
bx O
bx N
bx M
b100000 L
bx K
bx J
0I
bx H
bx G
bx F
bx E
bx D
0C
b10 B
0A
0@
0?
0>
0=
0<
0;
b0 :
09
bx 8
bx 7
bx 6
15
bx 4
bx 3
bx 2
bx 1
bx 0
bx00 /
bx .
bx00 -
bx ,
bx +
1*
x)
bx (
bx '
bx &
bx %
0$
1#
b1000000 "
1!
$end
#5000
0!
0*
#10000
1!
1*
#15000
0!
0*
#20000
b11111 8
b11111 K
b11111 +
b11111 X
0)
b11111 U
b11111 T
b11111 (
b0 '
b0 S
b1 N
b1 4
b1 Y
b11111 M
b11111 3
b11111 &
b11111 R
1=
1V
1A
1I
1>
19
b100 %
b100 0
b0 -
b1 7
b1 J
b100 1
b1111100001000000000000000000 /
b0 ,
b0 O
b0 6
b0 P
b1 H
b11111 G
b100 2
b0 E
b10001111111000010000000000000000 .
b10001111111000010000000000000000 F
1C
b0 D
1!
1*
0#
05
#25000
0!
0*
#30000
b10 N
b10 4
b10 Y
b1000 0
b10 7
b10 J
b1000 1
b1111100010000000000000000000 /
b10 H
b1000 %
b1000 2
b1 E
b10001111111000100000000000000000 .
b10001111111000100000000000000000 F
b100 D
1!
1*
#35000
0!
0*
#40000
bx +
bx X
b111110 U
b111110 8
b111110 K
b11 7
b11 J
b111110 T
b111110 (
b10 :
0=
0V
0>
09
1@
b11111 N
b11111 4
b11111 Y
b1100 0
b110000010000000 -
b11111 '
b11111 S
b1100 1
b100010000110000010000000 /
b100000 ,
b1100000100000 O
b1100000100000 6
b1100000100000 P
b1 G
b110000010001100 %
b1100 2
b10 E
b1000100001100000100000 .
b1000100001100000100000 F
b1000 D
1!
1*
#45000
0!
0*
#50000
1)
b0 U
b0 T
b0 (
bx 8
bx K
b0 '
b0 S
b111110 N
b111110 4
b111110 Y
b0 M
b0 3
b0 &
b0 R
b0 :
1?
1W
0A
0I
x>
19
x@
b10000 0
b0 -
b0xx 7
b0xx J
b10000 1
b11000000000000000000 /
b0 ,
b0 O
b0 6
b0 P
b11 H
b0 G
b10000 %
b10000 2
b11 E
b10101100000000110000000000000000 .
b10101100000000110000000000000000 F
b1100 D
1!
1*
#55000
0!
0*
#60000
0)
b11111 U
b11111 T
b11111 (
b11111 8
b11111 K
b11111 +
b11111 X
b11111 N
b11111 4
b11111 Y
b11111 M
b11111 3
b11111 &
b11111 R
0?
0W
1=
1V
1A
1I
1>
0@
b10100 0
b1 7
b1 J
b10100 1
b1111100001000000000000000000 /
b1 H
b11111 G
b10100 %
b10100 2
b100 E
b10001111111000010000000000000000 .
b10001111111000010000000000000000 F
b10000 D
1!
1*
#65000
0!
0*
#70000
b11110 8
b11110 K
b11110 +
b11110 X
b11110 U
b11110 T
b11110 (
b11110 M
b11110 3
b11110 &
b11110 R
b11000 0
b10 7
b10 J
b11000 1
b1111000010000000000000000000 /
b10 H
b11110 G
b11000 %
b11000 2
b101 E
b10001111110000100000000000000000 .
b10001111110000100000000000000000 F
b10100 D
1!
1*
#75000
0!
0*
#80000
b110 B
b110 Q
bx +
bx X
b1 U
b1 8
b1 K
b11 7
b11 J
b1 T
b1 (
b11111 M
b11111 3
b11111 &
b11111 R
b10 :
0=
0V
0>
09
1@
b11110 N
b11110 4
b11110 Y
b11100 0
b110000010001000 -
b11110 '
b11110 S
b11100 1
b100010000110000010001000 /
b100010 ,
b1100000100010 O
b1100000100010 6
b1100000100010 P
b1 G
b110000010100100 %
b11100 2
b110 E
b1000100001100000100010 .
b1000100001100000100010 F
b11000 D
1!
1*
#85000
0!
0*
#90000
1)
b0 U
b0 T
b0 (
bx 8
bx K
b0 '
b0 S
b10 B
b10 Q
b1 N
b1 4
b1 Y
b0 M
b0 3
b0 &
b0 R
b0 :
1?
1W
0A
0I
x>
19
x@
b100000 0
b0 -
b0xx 7
b0xx J
b100000 1
b11000000000000000000 /
b0 ,
b0 O
b0 6
b0 P
b11 H
b0 G
b100000 %
b100000 2
b111 E
b10101100000000110000000000000000 .
b10101100000000110000000000000000 F
b11100 D
1!
1*
#95000
0!
0*
#100000
b11001 8
b11001 K
b11001 +
b11001 X
0)
b11001 U
b11001 T
b11001 (
b11111 N
b11111 4
b11111 Y
0?
0W
1=
1V
1A
1I
1>
0@
b100100 0
b1100100 -
b11001 '
b11001 S
b1 7
b1 J
b100100 1
b1000000000001100100 /
b11001 ,
b11001 O
b11001 6
b11001 P
b1 H
b10001000 %
b100100 2
b1000 E
b10001100000000010000000000011001 .
b10001100000000010000000000011001 F
b100000 D
1!
1*
#105000
0!
0*
#110000
b10000 8
b10000 K
b10000 +
b10000 X
b10000 U
b10000 T
b10000 (
b11110 N
b11110 4
b11110 Y
b101000 0
b1000000 -
b10000 '
b10000 S
b10 7
b10 J
b101000 1
b10000000000001000000 /
b10000 ,
b10000 O
b10000 6
b10000 P
b10 H
b1101000 %
b101000 2
b1001 E
b10001100000000100000000000010000 .
b10001100000000100000000000010000 F
b100100 D
1!
1*
#115000
0!
0*
#120000
b1 B
b1 Q
bx +
bx X
b11001 U
b11001 8
b11001 K
b11 7
b11 J
b11001 T
b11001 (
b11001 M
b11001 3
b11001 &
b11001 R
b10 :
0=
0V
0>
09
1@
b10000 N
b10000 4
b10000 Y
b101100 0
b110000010010100 -
b10000 '
b10000 S
b101100 1
b100010000110000010010100 /
b100101 ,
b1100000100101 O
b1100000100101 6
b1100000100101 P
b1 G
b110000011000000 %
b101100 2
b1010 E
b1000100001100000100101 .
b1000100001100000100101 F
b101000 D
1!
1*
#125000
0!
0*
