mips/single_cycle/data_mem_64x32.v
`timescale 1ns/1ns

/*
	synchronous read and write memory unit
 */

module data_mem_64x32(clk, addr, rd, wd, memwrite, memread);

	/*
	 *	reg addr must be long enough to address the entire memory
	 */

	input clk;
	input [5:0] addr;
	output wire [31:0] rd;
	input [31:0] wd;
	input memwrite;
	input memread;

	reg [31:0] memory [0:63];

	integer i;

	initial begin
		for(i = 0; i < 64; i = i + 1)
			memory[i] <= i;
	end


	// data is not available until the next clock cycle
	always @(posedge clk) begin
		if (memwrite == 1'b1)
			memory[addr] <= wd;
	end

	assign rd = (memread == 1'b1) ? memory[addr] : 32'bX;

endmodule

mips/single_cycle/testbenches/data_mem_64x32_tb.v
`timescale 1ns/1ns

/*
	Write random values to memory, then read them
 */

module test_bench;

	reg clk_tb;

	// 100Mhz clock
	always #5 clk_tb = ~clk_tb;

	///////////////////////////////////////////////////////////////////////////
	//
	// 
	//	Instantiations
	//
	//
	///////////////////////////////////////////////////////////////////////////
	

	reg [5:0] addr_tb;
	wire [31:0] rd_tb;
	reg [31:0] wd_tb;
	reg memwrite_tb;
	reg memread_tb;

	data_mem_64x32 UUT(
		.clk(clk_tb),
		.addr(addr_tb),
		.rd(rd_tb),
		.wd(wd_tb),
		.memwrite(memwrite_tb),
		.memread(memread_tb)
		);

	///////////////////////////////////////////////////////////////////////////
	//
	// 
	//	Initializations
	//
	//
	///////////////////////////////////////////////////////////////////////////

	initial begin
		$dumpfile("simulation.vcd");
		$dumpvars(0, test_bench);
	end

	/*
		evaluation  ($random)
	 */

	reg start;
	reg [31:0] test_mem [0:63];
	wire [31:0] expected_data;
	integer num_errors = 0;

	initial addr_tb = 0;
	initial memwrite_tb = 0;
	initial memread_tb = 0;
	initial wd_tb = 0;

	initial begin
		clk_tb = 0;

		// clock is starting high
		// issues coming from write synchronization
		// need to consider the whole clock cycle and the read/write 
		// characteristics of the module
		memwrite_tb = 1'b1;
		repeat(64) begin
			wd_tb = $random;
			test_mem[addr_tb] = wd_tb;
			#10;
			addr_tb = addr_tb + 1;
		end

		memwrite_tb = 1'b0;
		addr_tb = 0;
		wd_tb = 32'bX;

		memread_tb = 1'b1;
		repeat(64) @(posedge clk_tb) begin
			if(test_mem[addr_tb] != rd_tb) begin
				$display("ERROR: q value %0x does not match the expected value %0x at address %d", 
					rd_tb, test_mem[addr_tb], addr_tb);
				//num_errors = num_errors + 1;
			end
			addr_tb = addr_tb + 1;
		end

		$finish;
	end

endmodule

mips/single_cycle/testbenches/simulation.vcd
$date
	Sun Dec 30 17:09:48 2018
$end
$version
	Icarus Verilog
$end
$timescale
	1ns
$end
$scope module test_bench $end
$var wire 32 ! rd_tb [31:0] $end
$var reg 6 " addr_tb [5:0] $end
$var reg 1 # clk_tb $end
$var reg 1 $ memread_tb $end
$var reg 1 % memwrite_tb $end
$var integer 32 & num_errors [31:0] $end
$var reg 32 ' wd_tb [31:0] $end
$scope module UUT $end
$var wire 6 ( addr [5:0] $end
$var wire 1 ) clk $end
$var wire 1 * memread $end
$var wire 1 + memwrite $end
$var wire 32 , rd [31:0] $end
$var wire 32 - wd [31:0] $end
$var integer 32 . i [31:0] $end
$upscope $end
$upscope $end
$enddefinitions $end
#0
$dumpvars
b1000000 .
b10010000101010011010100100100 -
bx ,
1+
0*
0)
b0 (
b10010000101010011010100100100 '
b0 &
1%
0$
0#
b0 "
bx !
$end
#5
1#
1)
#10
0#
0)
b11000000100010010101111010000001 '
b11000000100010010101111010000001 -
b1 "
b1 (
#15
1#
1)
#20
0#
0)
b10000100100001001101011000001001 '
b10000100100001001101011000001001 -
b10 "
b10 (
#25
1#
1)
#30
0#
0)
b10110001111100000101011001100011 '
b10110001111100000101011001100011 -
b11 "
b11 (
#35
1#
1)
#40
0#
0)
b110101110010111101100001101 '
b110101110010111101100001101 -
b100 "
b100 (
#45
1#
1)
#50
0#
0)
b1000110110111111001100110001101 '
b1000110110111111001100110001101 -
b101 "
b101 (
#55
1#
1)
#60
0#
0)
b10110010110000101000010001100101 '
b10110010110000101000010001100101 -
b110 "
b110 (
#65
1#
1)
#70
0#
0)
b10001001001101110101001000010010 '
b10001001001101110101001000010010 -
b111 "
b111 (
#75
1#
1)
#80
0#
0)
b111100111110001100000001 '
b111100111110001100000001 -
b1000 "
b1000 (
#85
1#
1)
#90
0#
0)
b110110101111100110100001101 '
b110110101111100110100001101 -
b1001 "
b1001 (
#95
1#
1)
#100
0#
0)
b111011001000111111000101110110 '
b111011001000111111000101110110 -
b1010 "
b1010 (
#105
1#
1)
#110
0#
0)
b11110100011011100110100111101 '
b11110100011011100110100111101 -
b1011 "
b1011 (
#115
1#
1)
#120
0#
0)
b1110110110101000101011111101101 '
b1110110110101000101011111101101 -
b1100 "
b1100 (
#125
1#
1)
#130
0#
0)
b1000110001011011111011110001100 '
b1000110001011011111011110001100 -
b1101 "
b1101 (
#135
1#
1)
#140
0#
0)
b1111100111111011110100111111001 '
b1111100111111011110100111111001 -
b1110 "
b1110 (
#145
1#
1)
#150
0#
0)
b11100011001101110010010011000110 '
b11100011001101110010010011000110 -
b1111 "
b1111 (
#155
1#
1)
#160
0#
0)
b11100010111101111000010011000101 '
b11100010111101111000010011000101 -
b10000 "
b10000 (
#165
1#
1)
#170
0#
0)
b11010101000100111101001010101010 '
b11010101000100111101001010101010 -
b10001 "
b10001 (
#175
1#
1)
#180
0#
0)
b1110010101011111111011111100101 '
b1110010101011111111011111100101 -
b10010 "
b10010 (
#185
1#
1)
#190
0#
0)
b10111011110100100111001001110111 '
b10111011110100100111001001110111 -
b10011 "
b10011 (
#195
1#
1)
#200
0#
0)
b10001001001100101101011000010010 '
b10001001001100101101011000010010 -
b10100 "
b10100 (
#205
1#
1)
#210
0#
0)
b1000111111011001101101110001111 '
b1000111111011001101101110001111 -
b10101 "
b10101 (
#215
1#
1)
#220
0#
0)
b1111001001100000110100111110010 '
b1111001001100000110100111110010 -
b10110 "
b10110 (
#225
1#
1)
#230
0#
0)
b11100111011101101001011011001110 '
b11100111011101101001011011001110 -
b10111 "
b10111 (
#235
1#
1)
#240
0#
0)
b11110100000000000111101011101000 '
b11110100000000000111101011101000 -
b11000 "
b11000 (
#245
1#
1)
#250
0#
0)
b11100010110010100100111011000101 '
b11100010110010100100111011000101 -
b11001 "
b11001 (
#255
1#
1)
#260
0#
0)
b101110010110000100100101011100 '
b101110010110000100100101011100 -
b11010 "
b11010 (
#265
1#
1)
#270
0#
0)
b11011110100011100010100010111101 '
b11011110100011100010100010111101 -
b11011 "
b11011 (
#275
1#
1)
#280
0#
0)
b10010110101010110101100000101101 '
b10010110101010110101100000101101 -
b11100 "
b11100 (
#285
1#
1)
#290
0#
0)
b10110010101001110010011001100101 '
b10110010101001110010011001100101 -
b11101 "
b11101 (
#295
1#
1)
#300
0#
0)
b10110001111011110110001001100011 '
b10110001111011110110001001100011 -
b11110 "
b11110 (
#305
1#
1)
#310
0#
0)
b101011100111000011100001010 '
b101011100111000011100001010 -
b11111 "
b11111 (
#315
1#
1)
#320
0#
0)
b11000000001110110010001010000000 '
b11000000001110110010001010000000 -
b100000 "
b100000 (
#325
1#
1)
#330
0#
0)
b10000011001000010000100100000 '
b10000011001000010000100100000 -
b100001 "
b100001 (
#335
1#
1)
#340
0#
0)
b1010101011110000100010110101010 '
b1010101011110000100010110101010 -
b100010 "
b100010 (
#345
1#
1)
#350
0#
0)
b11001110110011001100110010011101 '
b11001110110011001100110010011101 -
b100011 "
b100011 (
#355
1#
1)
#360
0#
0)
b11001011001000000011111010010110 '
b11001011001000000011111010010110 -
b100100 "
b100100 (
#365
1#
1)
#370
0#
0)
b10001001100000111011100000010011 '
b10001001100000111011100000010011 -
b100101 "
b100101 (
#375
1#
1)
#380
0#
0)
b10000110101111000011100000001101 '
b10000110101111000011100000001101 -
b100110 "
b100110 (
#385
1#
1)
#390
0#
0)
b10101001101001111101011001010011 '
b10101001101001111101011001010011 -
b100111 "
b100111 (
#395
1#
1)
#400
0#
0)
b110101100111111101110101101011 '
b110101100111111101110101101011 -
b101000 "
b101000 (
#405
1#
1)
#410
0#
0)
b11101010101001100010101011010101 '
b11101010101001100010101011010101 -
b101001 "
b101001 (
#415
1#
1)
#420
0#
0)
b10000001000101110100101000000010 '
b10000001000101110100101000000010 -
b101010 "
b101010 (
#425
1#
1)
#430
0#
0)
b11010111010101100011111010101110 '
b11010111010101100011111010101110 -
b101011 "
b101011 (
#435
1#
1)
#440
0#
0)
b1110111111111110100100011101 '
b1110111111111110100100011101 -
b101100 "
b101100 (
#445
1#
1)
#450
0#
0)
b11100111110001010111001011001111 '
b11100111110001010111001011001111 -
b101101 "
b101101 (
#455
1#
1)
#460
0#
0)
b10001100001000100100100100011 '
b10001100001000100100100100011 -
b101110 "
b101110 (
#465
1#
1)
#470
0#
0)
b101000010010110010100001010 '
b101000010010110010100001010 -
b101111 "
b101111 (
#475
1#
1)
#480
0#
0)
b11100101011100110000101011001010 '
b11100101011100110000101011001010 -
b110000 "
b110000 (
#485
1#
1)
#490
0#
0)
b10011110001100010100110000111100 '
b10011110001100010100110000111100 -
b110001 "
b110001 (
#495
1#
1)
#500
0#
0)
b1111001011010001011110111110010 '
b1111001011010001011110111110010 -
b110010 "
b110010 (
#505
1#
1)
#510
0#
0)
b1000101001011100110000110001010 '
b1000101001011100110000110001010 -
b110011 "
b110011 (
#515
1#
1)
#520
0#
0)
b100000110001001011001101000001 '
b100000110001001011001101000001 -
b110100 "
b110100 (
#525
1#
1)
#530
0#
0)
b11101100010010110011010011011000 '
b11101100010010110011010011011000 -
b110101 "
b110101 (
#535
1#
1)
#540
0#
0)
b111100001000001111001101111000 '
b111100001000001111001101111000 -
b110110 "
b110110 (
#545
1#
1)
#550
0#
0)
b11000100100010100001001010001001 '
b11000100100010100001001010001001 -
b110111 "
b110111 (
#555
1#
1)
#560
0#
0)
b1110101110001010000110111101011 '
b1110101110001010000110111101011 -
b111000 "
b111000 (
#565
1#
1)
#570
0#
0)
b1011011000000100110010110110110 '
b1011011000000100110010110110110 -
b111001 "
b111001 (
#575
1#
1)
#580
0#
0)
b1100011010010111111100111000110 '
b1100011010010111111100111000110 -
b111010 "
b111010 (
#585
1#
1)
#590
0#
0)
b1010111000101010001001110101110 '
b1010111000101010001001110101110 -
b111011 "
b111011 (
#595
1#
1)
#600
0#
0)
b11011110011101010000001010111100 '
b11011110011101010000001010111100 -
b111100 "
b111100 (
#605
1#
1)
#610
0#
0)
b10101000011111101110100101010 '
b10101000011111101110100101010 -
b111101 "
b111101 (
#615
1#
1)
#620
0#
0)
b10000101110101111001101000001011 '
b10000101110101111001101000001011 -
b111110 "
b111110 (
#625
1#
1)
#630
0#
0)
b10111000100101111011111001110001 '
b10111000100101111011111001110001 -
b111111 "
b111111 (
#635
1#
1)
#640
b10010000101010011010100100100 !
b10010000101010011010100100100 ,
0#
0)
1$
1*
bx '
bx -
0%
0+
b0 "
b0 (
#645
b11000000100010010101111010000001 !
b11000000100010010101111010000001 ,
b1 "
b1 (
1#
1)
#650
0#
0)
#655
b10000100100001001101011000001001 !
b10000100100001001101011000001001 ,
b10 "
b10 (
1#
1)
#660
0#
0)
#665
b10110001111100000101011001100011 !
b10110001111100000101011001100011 ,
b11 "
b11 (
1#
1)
#670
0#
0)
#675
b110101110010111101100001101 !
b110101110010111101100001101 ,
b100 "
b100 (
1#
1)
#680
0#
0)
#685
b1000110110111111001100110001101 !
b1000110110111111001100110001101 ,
b101 "
b101 (
1#
1)
#690
0#
0)
#695
b10110010110000101000010001100101 !
b10110010110000101000010001100101 ,
b110 "
b110 (
1#
1)
#700
0#
0)
#705
b10001001001101110101001000010010 !
b10001001001101110101001000010010 ,
b111 "
b111 (
1#
1)
#710
0#
0)
#715
b111100111110001100000001 !
b111100111110001100000001 ,
b1000 "
b1000 (
1#
1)
#720
0#
0)
#725
b110110101111100110100001101 !
b110110101111100110100001101 ,
b1001 "
b1001 (
1#
1)
#730
0#
0)
#735
b111011001000111111000101110110 !
b111011001000111111000101110110 ,
b1010 "
b1010 (
1#
1)
#740
0#
0)
#745
b11110100011011100110100111101 !
b11110100011011100110100111101 ,
b1011 "
b1011 (
1#
1)
#750
0#
0)
#755
b1110110110101000101011111101101 !
b1110110110101000101011111101101 ,
b1100 "
b1100 (
1#
1)
#760
0#
0)
#765
b1000110001011011111011110001100 !
b1000110001011011111011110001100 ,
b1101 "
b1101 (
1#
1)
#770
0#
0)
#775
b1111100111111011110100111111001 !
b1111100111111011110100111111001 ,
b1110 "
b1110 (
1#
1)
#780
0#
0)
#785
b11100011001101110010010011000110 !
b11100011001101110010010011000110 ,
b1111 "
b1111 (
1#
1)
#790
0#
0)
#795
b11100010111101111000010011000101 !
b11100010111101111000010011000101 ,
b10000 "
b10000 (
1#
1)
#800
0#
0)
#805
b11010101000100111101001010101010 !
b11010101000100111101001010101010 ,
b10001 "
b10001 (
1#
1)
#810
0#
0)
#815
b1110010101011111111011111100101 !
b1110010101011111111011111100101 ,
b10010 "
b10010 (
1#
1)
#820
0#
0)
#825
b10111011110100100111001001110111 !
b10111011110100100111001001110111 ,
b10011 "
b10011 (
1#
1)
#830
0#
0)
#835
b10001001001100101101011000010010 !
b10001001001100101101011000010010 ,
b10100 "
b10100 (
1#
1)
#840
0#
0)
#845
b1000111111011001101101110001111 !
b1000111111011001101101110001111 ,
b10101 "
b10101 (
1#
1)
#850
0#
0)
#855
b1111001001100000110100111110010 !
b1111001001100000110100111110010 ,
b10110 "
b10110 (
1#
1)
#860
0#
0)
#865
b11100111011101101001011011001110 !
b11100111011101101001011011001110 ,
b10111 "
b10111 (
1#
1)
#870
0#
0)
#875
b11110100000000000111101011101000 !
b11110100000000000111101011101000 ,
b11000 "
b11000 (
1#
1)
#880
0#
0)
#885
b11100010110010100100111011000101 !
b11100010110010100100111011000101 ,
b11001 "
b11001 (
1#
1)
#890
0#
0)
#895
b101110010110000100100101011100 !
b101110010110000100100101011100 ,
b11010 "
b11010 (
1#
1)
#900
0#
0)
#905
b11011110100011100010100010111101 !
b11011110100011100010100010111101 ,
b11011 "
b11011 (
1#
1)
#910
0#
0)
#915
b10010110101010110101100000101101 !
b10010110101010110101100000101101 ,
b11100 "
b11100 (
1#
1)
#920
0#
0)
#925
b10110010101001110010011001100101 !
b10110010101001110010011001100101 ,
b11101 "
b11101 (
1#
1)
#930
0#
0)
#935
b10110001111011110110001001100011 !
b10110001111011110110001001100011 ,
b11110 "
b11110 (
1#
1)
#940
0#
0)
#945
b101011100111000011100001010 !
b101011100111000011100001010 ,
b11111 "
b11111 (
1#
1)
#950
0#
0)
#955
b11000000001110110010001010000000 !
b11000000001110110010001010000000 ,
b100000 "
b100000 (
1#
1)
#960
0#
0)
#965
b10000011001000010000100100000 !
b10000011001000010000100100000 ,
b100001 "
b100001 (
1#
1)
#970
0#
0)
#975
b1010101011110000100010110101010 !
b1010101011110000100010110101010 ,
b100010 "
b100010 (
1#
1)
#980
0#
0)
#985
b11001110110011001100110010011101 !
b11001110110011001100110010011101 ,
b100011 "
b100011 (
1#
1)
#990
0#
0)
#995
b11001011001000000011111010010110 !
b11001011001000000011111010010110 ,
b100100 "
b100100 (
1#
1)
#1000
0#
0)
#1005
b10001001100000111011100000010011 !
b10001001100000111011100000010011 ,
b100101 "
b100101 (
1#
1)
#1010
0#
0)
#1015
b10000110101111000011100000001101 !
b10000110101111000011100000001101 ,
b100110 "
b100110 (
1#
1)
#1020
0#
0)
#1025
b10101001101001111101011001010011 !
b10101001101001111101011001010011 ,
b100111 "
b100111 (
1#
1)
#1030
0#
0)
#1035
b110101100111111101110101101011 !
b110101100111111101110101101011 ,
b101000 "
b101000 (
1#
1)
#1040
0#
0)
#1045
b11101010101001100010101011010101 !
b11101010101001100010101011010101 ,
b101001 "
b101001 (
1#
1)
#1050
0#
0)
#1055
b10000001000101110100101000000010 !
b10000001000101110100101000000010 ,
b101010 "
b101010 (
1#
1)
#1060
0#
0)
#1065
b11010111010101100011111010101110 !
b11010111010101100011111010101110 ,
b101011 "
b101011 (
1#
1)
#1070
0#
0)
#1075
b1110111111111110100100011101 !
b1110111111111110100100011101 ,
b101100 "
b101100 (
1#
1)
#1080
0#
0)
#1085
b11100111110001010111001011001111 !
b11100111110001010111001011001111 ,
b101101 "
b101101 (
1#
1)
#1090
0#
0)
#1095
b10001100001000100100100100011 !
b10001100001000100100100100011 ,
b101110 "
b101110 (
1#
1)
#1100
0#
0)
#1105
b101000010010110010100001010 !
b101000010010110010100001010 ,
b101111 "
b101111 (
1#
1)
#1110
0#
0)
#1115
b11100101011100110000101011001010 !
b11100101011100110000101011001010 ,
b110000 "
b110000 (
1#
1)
#1120
0#
0)
#1125
b10011110001100010100110000111100 !
b10011110001100010100110000111100 ,
b110001 "
b110001 (
1#
1)
#1130
0#
0)
#1135
b1111001011010001011110111110010 !
b1111001011010001011110111110010 ,
b110010 "
b110010 (
1#
1)
#1140
0#
0)
#1145
b1000101001011100110000110001010 !
b1000101001011100110000110001010 ,
b110011 "
b110011 (
1#
1)
#1150
0#
0)
#1155
b100000110001001011001101000001 !
b100000110001001011001101000001 ,
b110100 "
b110100 (
1#
1)
#1160
0#
0)
#1165
b11101100010010110011010011011000 !
b11101100010010110011010011011000 ,
b110101 "
b110101 (
1#
1)
#1170
0#
0)
#1175
b111100001000001111001101111000 !
b111100001000001111001101111000 ,
b110110 "
b110110 (
1#
1)
#1180
0#
0)
#1185
b11000100100010100001001010001001 !
b11000100100010100001001010001001 ,
b110111 "
b110111 (
1#
1)
#1190
0#
0)
#1195
b1110101110001010000110111101011 !
b1110101110001010000110111101011 ,
b111000 "
b111000 (
1#
1)
#1200
0#
0)
#1205
b1011011000000100110010110110110 !
b1011011000000100110010110110110 ,
b111001 "
b111001 (
1#
1)
#1210
0#
0)
#1215
b1100011010010111111100111000110 !
b1100011010010111111100111000110 ,
b111010 "
b111010 (
1#
1)
#1220
0#
0)
#1225
b1010111000101010001001110101110 !
b1010111000101010001001110101110 ,
b111011 "
b111011 (
1#
1)
#1230
0#
0)
#1235
b11011110011101010000001010111100 !
b11011110011101010000001010111100 ,
b111100 "
b111100 (
1#
1)
#1240
0#
0)
#1245
b10101000011111101110100101010 !
b10101000011111101110100101010 ,
b111101 "
b111101 (
1#
1)
#1250
0#
0)
#1255
b10000101110101111001101000001011 !
b10000101110101111001101000001011 ,
b111110 "
b111110 (
1#
1)
#1260
0#
0)
#1265
b10111000100101111011111001110001 !
b10111000100101111011111001110001 ,
b111111 "
b111111 (
1#
1)
#1270
0#
0)
#1275
b10010000101010011010100100100 !
b10010000101010011010100100100 ,
b0 "
b0 (
1#
1)
