mips/single_cycle/sign_ext_16_32.v
`timescale 1 ns / 100 ps

/*
	16 to 32 bit sign extender
*/

module sign_ext_16_32(d, q);
	input [15:0] d;
	output [31:0] q;

	assign q = { {16{d[15]}}, d};

endmodule

mips/single_cycle/testbenches/sign_ext_16_32_tb.v
`timescale 1ns/1ns

/*
	iverilog sign_ext_16_32_tb.v ../sign_ext_16_32.v
 */

module test_bench;

	reg clk_tb = 1;
	// 100Mhz clock
	always #5 clk_tb = ~clk_tb;

	reg [15:0] d_tb;
	wire [31:0] q_tb;

	sign_ext_16_32 UUT(
			.d(d_tb),
			.q(q_tb)
		);

	always @(posedge clk_tb) d_tb <= $random;

	initial begin
		repeat(1000) @(posedge clk_tb);
		$finish;
	end

	initial begin
		$dumpfile("simulation.vcd");
		$dumpvars;
	end

	/*
		evaluation
	 */

	wire [31:0] expected_q;
	assign expected_q = { {16{d_tb[15]}}, d_tb};

	integer num_checks = 0;
	integer num_errors = 0;
	always @(posedge clk_tb) begin
		num_checks = num_checks + 1;
		if(expected_q != q_tb) begin
			$display("ERROR: q value %0x does not match the expected value %0x at time %0fns", 
				q_tb, expected_q, $realtime);
			num_errors = num_errors + 1;
		end
	end

endmodule

mips/single_cycle/testbenches/simulation.vcd
$date
	Sat Dec 29 15:48:55 2018
$end
$version
	Icarus Verilog
$end
$timescale
	100ps
$end
$scope module test_bench $end
$var wire 32 ! expected_q [31:0] $end
$var wire 32 " q_tb [31:0] $end
$var reg 1 # clk_tb $end
$var reg 16 $ d_tb [15:0] $end
$var integer 32 % num_checks [31:0] $end
$var integer 32 & num_errors [31:0] $end
$scope module UUT $end
$var wire 16 ' d [15:0] $end
$var wire 32 ( q [31:0] $end
$upscope $end
$upscope $end
$enddefinitions $end
#0
$dumpvars
bx (
bx '
b0 &
b0 %
bx $
1#
bx "
bx !
$end
#50
0#
#100
b11010100100100 $
b11010100100100 !
b11010100100100 '
b11010100100100 "
b11010100100100 (
b1 %
1#
#150
0#
#200
b101111010000001 $
b101111010000001 !
b101111010000001 '
b101111010000001 "
b101111010000001 (
b10 %
1#
#250
0#
#300
b1101011000001001 $
b11111111111111111101011000001001 !
b1101011000001001 '
b11111111111111111101011000001001 "
b11111111111111111101011000001001 (
b11 %
1#
#350
0#
#400
b101011001100011 $
b101011001100011 !
b101011001100011 '
b101011001100011 "
b101011001100011 (
b100 %
1#
#450
0#
#500
b111101100001101 $
b111101100001101 !
b111101100001101 '
b111101100001101 "
b111101100001101 (
b101 %
1#
#550
0#
#600
b1001100110001101 $
b11111111111111111001100110001101 !
b1001100110001101 '
b11111111111111111001100110001101 "
b11111111111111111001100110001101 (
b110 %
1#
#650
0#
#700
b1000010001100101 $
b11111111111111111000010001100101 !
b1000010001100101 '
b11111111111111111000010001100101 "
b11111111111111111000010001100101 (
b111 %
1#
#750
0#
#800
b101001000010010 $
b101001000010010 !
b101001000010010 '
b101001000010010 "
b101001000010010 (
b1000 %
1#
#850
0#
#900
b1110001100000001 $
b11111111111111111110001100000001 !
b1110001100000001 '
b11111111111111111110001100000001 "
b11111111111111111110001100000001 (
b1001 %
1#
#950
0#
#1000
b1100110100001101 $
b11111111111111111100110100001101 !
b1100110100001101 '
b11111111111111111100110100001101 "
b11111111111111111100110100001101 (
b1010 %
1#
#1050
0#
#1100
b1111000101110110 $
b11111111111111111111000101110110 !
b1111000101110110 '
b11111111111111111111000101110110 "
b11111111111111111111000101110110 (
b1011 %
1#
#1150
0#
#1200
b1100110100111101 $
b11111111111111111100110100111101 !
b1100110100111101 '
b11111111111111111100110100111101 "
b11111111111111111100110100111101 (
b1100 %
1#
#1250
0#
#1300
b101011111101101 $
b101011111101101 !
b101011111101101 '
b101011111101101 "
b101011111101101 (
b1101 %
1#
#1350
0#
#1400
b1111011110001100 $
b11111111111111111111011110001100 !
b1111011110001100 '
b11111111111111111111011110001100 "
b11111111111111111111011110001100 (
b1110 %
1#
#1450
0#
#1500
b1110100111111001 $
b11111111111111111110100111111001 !
b1110100111111001 '
b11111111111111111110100111111001 "
b11111111111111111110100111111001 (
b1111 %
1#
#1550
0#
#1600
b10010011000110 $
b10010011000110 !
b10010011000110 '
b10010011000110 "
b10010011000110 (
b10000 %
1#
#1650
0#
#1700
b1000010011000101 $
b11111111111111111000010011000101 !
b1000010011000101 '
b11111111111111111000010011000101 "
b11111111111111111000010011000101 (
b10001 %
1#
#1750
0#
#1800
b1101001010101010 $
b11111111111111111101001010101010 !
b1101001010101010 '
b11111111111111111101001010101010 "
b11111111111111111101001010101010 (
b10010 %
1#
#1850
0#
#1900
b1111011111100101 $
b11111111111111111111011111100101 !
b1111011111100101 '
b11111111111111111111011111100101 "
b11111111111111111111011111100101 (
b10011 %
1#
#1950
0#
#2000
b111001001110111 $
b111001001110111 !
b111001001110111 '
b111001001110111 "
b111001001110111 (
b10100 %
1#
#2050
0#
#2100
b1101011000010010 $
b11111111111111111101011000010010 !
b1101011000010010 '
b11111111111111111101011000010010 "
b11111111111111111101011000010010 (
b10101 %
1#
#2150
0#
#2200
b1101101110001111 $
b11111111111111111101101110001111 !
b1101101110001111 '
b11111111111111111101101110001111 "
b11111111111111111101101110001111 (
b10110 %
1#
#2250
0#
#2300
b110100111110010 $
b110100111110010 !
b110100111110010 '
b110100111110010 "
b110100111110010 (
b10111 %
1#
#2350
0#
#2400
b1001011011001110 $
b11111111111111111001011011001110 !
b1001011011001110 '
b11111111111111111001011011001110 "
b11111111111111111001011011001110 (
b11000 %
1#
#2450
0#
#2500
b111101011101000 $
b111101011101000 !
b111101011101000 '
b111101011101000 "
b111101011101000 (
b11001 %
1#
#2550
0#
#2600
b100111011000101 $
b100111011000101 !
b100111011000101 '
b100111011000101 "
b100111011000101 (
b11010 %
1#
#2650
0#
#2700
b100100101011100 $
b100100101011100 !
b100100101011100 '
b100100101011100 "
b100100101011100 (
b11011 %
1#
#2750
0#
#2800
b10100010111101 $
b10100010111101 !
b10100010111101 '
b10100010111101 "
b10100010111101 (
b11100 %
1#
#2850
0#
#2900
b101100000101101 $
b101100000101101 !
b101100000101101 '
b101100000101101 "
b101100000101101 (
b11101 %
1#
#2950
0#
#3000
b10011001100101 $
b10011001100101 !
b10011001100101 '
b10011001100101 "
b10011001100101 (
b11110 %
1#
#3050
0#
#3100
b110001001100011 $
b110001001100011 !
b110001001100011 '
b110001001100011 "
b110001001100011 (
b11111 %
1#
#3150
0#
#3200
b1000011100001010 $
b11111111111111111000011100001010 !
b1000011100001010 '
b11111111111111111000011100001010 "
b11111111111111111000011100001010 (
b100000 %
1#
#3250
0#
#3300
b10001010000000 $
b10001010000000 !
b10001010000000 '
b10001010000000 "
b10001010000000 (
b100001 %
1#
#3350
0#
#3400
b10000100100000 $
b10000100100000 !
b10000100100000 '
b10000100100000 "
b10000100100000 (
b100010 %
1#
#3450
0#
#3500
b100010110101010 $
b100010110101010 !
b100010110101010 '
b100010110101010 "
b100010110101010 (
b100011 %
1#
#3550
0#
#3600
b1100110010011101 $
b11111111111111111100110010011101 !
b1100110010011101 '
b11111111111111111100110010011101 "
b11111111111111111100110010011101 (
b100100 %
1#
#3650
0#
#3700
b11111010010110 $
b11111010010110 !
b11111010010110 '
b11111010010110 "
b11111010010110 (
b100101 %
1#
#3750
0#
#3800
b1011100000010011 $
b11111111111111111011100000010011 !
b1011100000010011 '
b11111111111111111011100000010011 "
b11111111111111111011100000010011 (
b100110 %
1#
#3850
0#
#3900
b11100000001101 $
b11100000001101 !
b11100000001101 '
b11100000001101 "
b11100000001101 (
b100111 %
1#
#3950
0#
#4000
b1101011001010011 $
b11111111111111111101011001010011 !
b1101011001010011 '
b11111111111111111101011001010011 "
b11111111111111111101011001010011 (
b101000 %
1#
#4050
0#
#4100
b1101110101101011 $
b11111111111111111101110101101011 !
b1101110101101011 '
b11111111111111111101110101101011 "
b11111111111111111101110101101011 (
b101001 %
1#
#4150
0#
#4200
b10101011010101 $
b10101011010101 !
b10101011010101 '
b10101011010101 "
b10101011010101 (
b101010 %
1#
#4250
0#
#4300
b100101000000010 $
b100101000000010 !
b100101000000010 '
b100101000000010 "
b100101000000010 (
b101011 %
1#
#4350
0#
#4400
b11111010101110 $
b11111010101110 !
b11111010101110 '
b11111010101110 "
b11111010101110 (
b101100 %
1#
#4450
0#
#4500
b1110100100011101 $
b11111111111111111110100100011101 !
b1110100100011101 '
b11111111111111111110100100011101 "
b11111111111111111110100100011101 (
b101101 %
1#
#4550
0#
#4600
b111001011001111 $
b111001011001111 !
b111001011001111 '
b111001011001111 "
b111001011001111 (
b101110 %
1#
#4650
0#
#4700
b100100100100011 $
b100100100100011 !
b100100100100011 '
b100100100100011 "
b100100100100011 (
b101111 %
1#
#4750
0#
#4800
b110010100001010 $
b110010100001010 !
b110010100001010 '
b110010100001010 "
b110010100001010 (
b110000 %
1#
#4850
0#
#4900
b101011001010 $
b101011001010 !
b101011001010 '
b101011001010 "
b101011001010 (
b110001 %
1#
#4950
0#
#5000
b100110000111100 $
b100110000111100 !
b100110000111100 '
b100110000111100 "
b100110000111100 (
b110010 %
1#
#5050
0#
#5100
b1011110111110010 $
b11111111111111111011110111110010 !
b1011110111110010 '
b11111111111111111011110111110010 "
b11111111111111111011110111110010 (
b110011 %
1#
#5150
0#
#5200
b110000110001010 $
b110000110001010 !
b110000110001010 '
b110000110001010 "
b110000110001010 (
b110100 %
1#
#5250
0#
#5300
b1011001101000001 $
b11111111111111111011001101000001 !
b1011001101000001 '
b11111111111111111011001101000001 "
b11111111111111111011001101000001 (
b110101 %
1#
#5350
0#
#5400
b11010011011000 $
b11010011011000 !
b11010011011000 '
b11010011011000 "
b11010011011000 (
b110110 %
1#
#5450
0#
#5500
b1111001101111000 $
b11111111111111111111001101111000 !
b1111001101111000 '
b11111111111111111111001101111000 "
b11111111111111111111001101111000 (
b110111 %
1#
#5550
0#
#5600
b1001010001001 $
b1001010001001 !
b1001010001001 '
b1001010001001 "
b1001010001001 (
b111000 %
1#
#5650
0#
#5700
b110111101011 $
b110111101011 !
b110111101011 '
b110111101011 "
b110111101011 (
b111001 %
1#
#5750
0#
#5800
b110010110110110 $
b110010110110110 !
b110010110110110 '
b110010110110110 "
b110010110110110 (
b111010 %
1#
#5850
0#
#5900
b1111100111000110 $
b11111111111111111111100111000110 !
b1111100111000110 '
b11111111111111111111100111000110 "
b11111111111111111111100111000110 (
b111011 %
1#
#5950
0#
#6000
b1001110101110 $
b1001110101110 !
b1001110101110 '
b1001110101110 "
b1001110101110 (
b111100 %
1#
#6050
0#
#6100
b1010111100 $
b1010111100 !
b1010111100 '
b1010111100 "
b1010111100 (
b111101 %
1#
#6150
0#
#6200
b1101110100101010 $
b11111111111111111101110100101010 !
b1101110100101010 '
b11111111111111111101110100101010 "
b11111111111111111101110100101010 (
b111110 %
1#
#6250
0#
#6300
b1001101000001011 $
b11111111111111111001101000001011 !
b1001101000001011 '
b11111111111111111001101000001011 "
b11111111111111111001101000001011 (
b111111 %
1#
#6350
0#
#6400
b1011111001110001 $
b11111111111111111011111001110001 !
b1011111001110001 '
b11111111111111111011111001110001 "
b11111111111111111011111001110001 (
b1000000 %
1#
#6450
0#
#6500
b100000110000101 $
b100000110000101 !
b100000110000101 '
b100000110000101 "
b100000110000101 (
b1000001 %
1#
#6550
0#
#6600
b101010101001111 $
b101010101001111 !
b101010101001111 '
b101010101001111 "
b101010101001111 (
b1000010 %
1#
#6650
0#
#6700
b110000000111011 $
b110000000111011 !
b110000000111011 '
b110000000111011 "
b110000000111011 (
b1000011 %
1#
#6750
0#
#6800
b11001100111010 $
b11001100111010 !
b11001100111010 '
b11001100111010 "
b11001100111010 (
b1000100 %
1#
#6850
0#
#6900
b11001001111110 $
b11001001111110 !
b11001001111110 '
b11001001111110 "
b11001001111110 (
b1000101 %
1#
#6950
0#
#7000
b100101100010101 $
b100101100010101 !
b100101100010101 '
b100101100010101 "
b100101100010101 (
b1000110 %
1#
#7050
0#
#7100
b1001101111110001 $
b11111111111111111001101111110001 !
b1001101111110001 '
b11111111111111111001101111110001 "
b11111111111111111001101111110001 (
b1000111 %
1#
#7150
0#
#7200
b100101111011001 $
b100101111011001 !
b100101111011001 '
b100101111011001 "
b100101111011001 (
b1001000 %
1#
#7250
0#
#7300
b11101100010 $
b11101100010 !
b11101100010 '
b11101100010 "
b11101100010 (
b1001001 %
1#
#7350
0#
#7400
b1111101101001100 $
b11111111111111111111101101001100 !
b1111101101001100 '
b11111111111111111111101101001100 "
b11111111111111111111101101001100 (
b1001010 %
1#
#7450
0#
#7500
b101010110011111 $
b101010110011111 !
b101010110011111 '
b101010110011111 "
b101010110011111 (
b1001011 %
1#
#7550
0#
#7600
b1010000110001111 $
b11111111111111111010000110001111 !
b1010000110001111 '
b11111111111111111010000110001111 "
b11111111111111111010000110001111 (
b1001100 %
1#
#7650
0#
#7700
b1010100111111000 $
b11111111111111111010100111111000 !
b1010100111111000 '
b11111111111111111010100111111000 "
b11111111111111111010100111111000 (
b1001101 %
1#
#7750
0#
#7800
b110000010110111 $
b110000010110111 !
b110000010110111 '
b110000010110111 "
b110000010110111 (
b1001110 %
1#
#7850
0#
#7900
b101011010011111 $
b101011010011111 !
b101011010011111 '
b101011010011111 "
b101011010011111 (
b1001111 %
1#
#7950
0#
#8000
b1001010001011100 $
b11111111111111111001010001011100 !
b1001010001011100 '
b11111111111111111001010001011100 "
b11111111111111111001010001011100 (
b1010000 %
1#
#8050
0#
#8100
b1100000001011011 $
b11111111111111111100000001011011 !
b1100000001011011 '
b11111111111111111100000001011011 "
b11111111111111111100000001011011 (
b1010001 %
1#
#8150
0#
#8200
b11011110001001 $
b11011110001001 !
b11011110001001 '
b11011110001001 "
b11011110001001 (
b1010010 %
1#
#8250
0#
#8300
b11001001001001 $
b11001001001001 !
b11001001001001 '
b11001001001001 "
b11001001001001 (
b1010011 %
1#
#8350
0#
#8400
b11111011010000 $
b11111011010000 !
b11111011010000 '
b11111011010000 "
b11111011010000 (
b1010100 %
1#
#8450
0#
#8500
b1100000011010111 $
b11111111111111111100000011010111 !
b1100000011010111 '
b11111111111111111100000011010111 "
b11111111111111111100000011010111 (
b1010101 %
1#
#8550
0#
#8600
b1111110001010001 $
b11111111111111111111110001010001 !
b1111110001010001 '
b11111111111111111111110001010001 "
b11111111111111111111110001010001 (
b1010110 %
1#
#8650
0#
#8700
b10111110010110 $
b10111110010110 !
b10111110010110 '
b10111110010110 "
b10111110010110 (
b1010111 %
1#
#8750
0#
#8800
b111111100001100 $
b111111100001100 !
b111111100001100 '
b111111100001100 "
b111111100001100 (
b1011000 %
1#
#8850
0#
#8900
b1100111011000010 $
b11111111111111111100111011000010 !
b1100111011000010 '
b11111111111111111100111011000010 "
b11111111111111111100111011000010 (
b1011001 %
1#
#8950
0#
#9000
b1110110111001000 $
b11111111111111111110110111001000 !
b1110110111001000 '
b11111111111111111110110111001000 "
b11111111111111111110110111001000 (
b1011010 %
1#
#9050
0#
#9100
b101101001110111 $
b101101001110111 !
b101101001110111 '
b101101001110111 "
b101101001110111 (
b1011011 %
1#
#9150
0#
#9200
b1110110100111101 $
b11111111111111111110110100111101 !
b1110110100111101 '
b11111111111111111110110100111101 "
b11111111111111111110110100111101 (
b1011100 %
1#
#9250
0#
#9300
b1101101100010010 $
b11111111111111111101101100010010 !
b1101101100010010 '
b11111111111111111101101100010010 "
b11111111111111111101101100010010 (
b1011101 %
1#
#9350
0#
#9400
b1111110 $
b1111110 !
b1111110 '
b1111110 "
b1111110 (
b1011110 %
1#
#9450
0#
#9500
b1000000101101101 $
b11111111111111111000000101101101 !
b1000000101101101 '
b11111111111111111000000101101101 "
b11111111111111111000000101101101 (
b1011111 %
1#
#9550
0#
#9600
b1110011100111001 $
b11111111111111111110011100111001 !
b1110011100111001 '
b11111111111111111110011100111001 "
b11111111111111111110011100111001 (
b1100000 %
1#
#9650
0#
#9700
b1000111100011111 $
b11111111111111111000111100011111 !
b1000111100011111 '
b11111111111111111000111100011111 "
b11111111111111111000111100011111 (
b1100001 %
1#
#9750
0#
#9800
b1111011011010011 $
b11111111111111111111011011010011 !
b1111011011010011 '
b11111111111111111111011011010011 "
b11111111111111111111011011010011 (
b1100010 %
1#
#9850
0#
#9900
b10111110000101 $
b10111110000101 !
b10111110000101 '
b10111110000101 "
b10111110000101 (
b1100011 %
1#
#9950
0#
#10000
b1000100001111000 $
b11111111111111111000100001111000 !
b1000100001111000 '
b11111111111111111000100001111000 "
b11111111111111111000100001111000 (
b1100100 %
1#
#10050
0#
#10100
b101100101011011 $
b101100101011011 !
b101100101011011 '
b101100101011011 "
b101100101011011 (
b1100101 %
1#
#10150
0#
#10200
b100101101001001 $
b100101101001001 !
b100101101001001 '
b100101101001001 "
b100101101001001 (
b1100110 %
1#
#10250
0#
#10300
b1010111000111111 $
b11111111111111111010111000111111 !
b1010111000111111 '
b11111111111111111010111000111111 "
b11111111111111111010111000111111 (
b1100111 %
1#
#10350
0#
#10400
b1010111100101010 $
b11111111111111111010111100101010 !
b1010111100101010 '
b11111111111111111010111100101010 "
b11111111111111111010111100101010 (
b1101000 %
1#
#10450
0#
#10500
b110001101011000 $
b110001101011000 !
b110001101011000 '
b110001101011000 "
b110001101011000 (
b1101001 %
1#
#10550
0#
#10600
b11100010000110 $
b11100010000110 !
b11100010000110 '
b11100010000110 "
b11100010000110 (
b1101010 %
1#
#10650
0#
#10700
b110010001110 $
b110010001110 !
b110010001110 '
b110010001110 "
b110010001110 (
b1101011 %
1#
#10750
0#
#10800
b1111001010011100 $
b11111111111111111111001010011100 !
b1111001010011100 '
b11111111111111111111001010011100 "
b11111111111111111111001010011100 (
b1101100 %
1#
#10850
0#
#10900
b1001100111111010 $
b11111111111111111001100111111010 !
b1001100111111010 '
b11111111111111111001100111111010 "
b11111111111111111001100111111010 (
b1101101 %
1#
#10950
0#
#11000
b1011110000100110 $
b11111111111111111011110000100110 !
b1011110000100110 '
b11111111111111111011110000100110 "
b11111111111111111011110000100110 (
b1101110 %
1#
#11050
0#
#11100
b1011101110011 $
b1011101110011 !
b1011101110011 '
b1011101110011 "
b1011101110011 (
b1101111 %
1#
#11150
0#
#11200
b1011010010100011 $
b11111111111111111011010010100011 !
b1011010010100011 '
b11111111111111111011010010100011 "
b11111111111111111011010010100011 (
b1110000 %
1#
#11250
0#
#11300
b1010100000101111 $
b11111111111111111010100000101111 !
b1010100000101111 '
b11111111111111111010100000101111 "
b11111111111111111010100000101111 (
b1110001 %
1#
#11350
0#
#11400
b1001001010110011 $
b11111111111111111001001010110011 !
b1001001010110011 '
b11111111111111111001001010110011 "
b11111111111111111001001010110011 (
b1110010 %
1#
#11450
0#
#11500
b101011001011111 $
b101011001011111 !
b101011001011111 '
b101011001011111 "
b101011001011111 (
b1110011 %
1#
#11550
0#
#11600
b110101000100 $
b110101000100 !
b110101000100 '
b110101000100 "
b110101000100 (
b1110100 %
1#
#11650
0#
#11700
b1111110111110111 $
b11111111111111111111110111110111 !
b1111110111110111 '
b11111111111111111111110111110111 "
b11111111111111111111110111110111 (
b1110101 %
1#
#11750
0#
#11800
b11011011001011 $
b11011011001011 !
b11011011001011 '
b11011011001011 "
b11011011001011 (
b1110110 %
1#
#11850
0#
#11900
b1101011100110 $
b1101011100110 !
b1101011100110 '
b1101011100110 "
b1101011100110 (
b1110111 %
1#
#11950
0#
#12000
b1101101101011010 $
b11111111111111111101101101011010 !
b1101101101011010 '
b11111111111111111101101101011010 "
b11111111111111111101101101011010 (
b1111000 %
1#
#12050
0#
#12100
b1100000100101001 $
b11111111111111111100000100101001 !
b1100000100101001 '
b11111111111111111100000100101001 "
b11111111111111111100000100101001 (
b1111001 %
1#
#12150
0#
#12200
b1110001011101101 $
b11111111111111111110001011101101 !
b1110001011101101 '
b11111111111111111110001011101101 "
b11111111111111111110001011101101 (
b1111010 %
1#
#12250
0#
#12300
b110110011011010 $
b110110011011010 !
b110110011011010 '
b110110011011010 "
b110110011011010 (
b1111011 %
1#
#12350
0#
#12400
b1011011001100101 $
b11111111111111111011011001100101 !
b1011011001100101 '
b11111111111111111011011001100101 "
b11111111111111111011011001100101 (
b1111100 %
1#
#12450
0#
#12500
b1110001010110101 $
b11111111111111111110001010110101 !
b1110001010110101 '
b11111111111111111110001010110101 "
b11111111111111111110001010110101 (
b1111101 %
1#
#12550
0#
#12600
b1001010011011111 $
b11111111111111111001010011011111 !
b1001010011011111 '
b11111111111111111001010011011111 "
b11111111111111111001010011011111 (
b1111110 %
1#
#12650
0#
#12700
b1100101111001 $
b1100101111001 !
b1100101111001 '
b1100101111001 "
b1100101111001 (
b1111111 %
1#
#12750
0#
#12800
b1111111101000100 $
b11111111111111111111111101000100 !
b1111111101000100 '
b11111111111111111111111101000100 "
b11111111111111111111111101000100 (
b10000000 %
1#
#12850
0#
#12900
b110011010000 $
b110011010000 !
b110011010000 '
b110011010000 "
b110011010000 (
b10000001 %
1#
#12950
0#
#13000
b101100101010 $
b101100101010 !
b101100101010 '
b101100101010 "
b101100101010 (
b10000010 %
1#
#13050
0#
#13100
b1010110110101011 $
b11111111111111111010110110101011 !
b1010110110101011 '
b11111111111111111010110110101011 "
b11111111111111111010110110101011 (
b10000011 %
1#
#13150
0#
#13200
b1100111100001110 $
b11111111111111111100111100001110 !
b1100111100001110 '
b11111111111111111100111100001110 "
b11111111111111111100111100001110 (
b10000100 %
1#
#13250
0#
#13300
b1010110111011100 $
b11111111111111111010110111011100 !
b1010110111011100 '
b11111111111111111010110111011100 "
b11111111111111111010110111011100 (
b10000101 %
1#
#13350
0#
#13400
b1011110010011010 $
b11111111111111111011110010011010 !
b1011110010011010 '
b11111111111111111011110010011010 "
b11111111111111111011110010011010 (
b10000110 %
1#
#13450
0#
#13500
b111001011111101 $
b111001011111101 !
b111001011111101 '
b111001011111101 "
b111001011111101 (
b10000111 %
1#
#13550
0#
#13600
b1011000011 $
b1011000011 !
b1011000011 '
b1011000011 "
b1011000011 (
b10001000 %
1#
#13650
0#
#13700
b1110110101010110 $
b11111111111111111110110101010110 !
b1110110101010110 '
b11111111111111111110110101010110 "
b11111111111111111110110101010110 (
b10001001 %
1#
#13750
0#
#13800
b1110100101001110 $
b11111111111111111110100101001110 !
b1110100101001110 '
b11111111111111111110100101001110 "
b11111111111111111110100101001110 (
b10001010 %
1#
#13850
0#
#13900
b111011001100111 $
b111011001100111 !
b111011001100111 '
b111011001100111 "
b111011001100111 (
b10001011 %
1#
#13950
0#
#14000
b11010000001010 $
b11010000001010 !
b11010000001010 '
b11010000001010 "
b11010000001010 (
b10001100 %
1#
#14050
0#
#14100
b1011100110110110 $
b11111111111111111011100110110110 !
b1011100110110110 '
b11111111111111111011100110110110 "
b11111111111111111011100110110110 (
b10001101 %
1#
#14150
0#
#14200
b1000101000111000 $
b11111111111111111000101000111000 !
b1000101000111000 '
b11111111111111111000101000111000 "
b11111111111111111000101000111000 (
b10001110 %
1#
#14250
0#
#14300
b1000011101111001 $
b11111111111111111000011101111001 !
b1000011101111001 '
b11111111111111111000011101111001 "
b11111111111111111000011101111001 (
b10001111 %
1#
#14350
0#
#14400
b1100010010111000 $
b11111111111111111100010010111000 !
b1100010010111000 '
b11111111111111111100010010111000 "
b11111111111111111100010010111000 (
b10010000 %
1#
#14450
0#
#14500
b1011111110010100 $
b11111111111111111011111110010100 !
b1011111110010100 '
b11111111111111111011111110010100 "
b11111111111111111011111110010100 (
b10010001 %
1#
#14550
0#
#14600
b101110110010011 $
b101110110010011 !
b101110110010011 '
b101110110010011 "
b101110110010011 (
b10010010 %
1#
#14650
0#
#14700
b10110000000100 $
b10110000000100 !
b10110000000100 '
b10110000000100 "
b10110000000100 (
b10010011 %
1#
#14750
0#
#14800
b1100101001011001 $
b11111111111111111100101001011001 !
b1100101001011001 '
b11111111111111111100101001011001 "
b11111111111111111100101001011001 (
b10010100 %
1#
#14850
0#
#14900
b110100111011011 $
b110100111011011 !
b110100111011011 '
b110100111011011 "
b110100111011011 (
b10010101 %
1#
#14950
0#
#15000
b1101111001001101 $
b11111111111111111101111001001101 !
b1101111001001101 '
b11111111111111111101111001001101 "
b11111111111111111101111001001101 (
b10010110 %
1#
#15050
0#
#15100
b1011011111011001 $
b11111111111111111011011111011001 !
b1011011111011001 '
b11111111111111111011011111011001 "
b11111111111111111011011111011001 (
b10010111 %
1#
#15150
0#
#15200
b10011001101101 $
b10011001101101 !
b10011001101101 '
b10011001101101 "
b10011001101101 (
b10011000 %
1#
#15250
0#
#15300
b1110001001110110 $
b11111111111111111110001001110110 !
b1110001001110110 '
b11111111111111111110001001110110 "
b11111111111111111110001001110110 (
b10011001 %
1#
#15350
0#
#15400
b100100111001010 $
b100100111001010 !
b100100111001010 '
b100100111001010 "
b100100111001010 (
b10011010 %
1#
#15450
0#
#15500
b10110110110110 $
b10110110110110 !
b10110110110110 '
b10110110110110 "
b10110110110110 (
b10011011 %
1#
#15550
0#
#15600
b111000110010101 $
b111000110010101 !
b111000110010101 '
b111000110010101 "
b111000110010101 (
b10011100 %
1#
#15650
0#
#15700
b1101001000110 $
b1101001000110 !
b1101001000110 '
b1101001000110 "
b1101001000110 (
b10011101 %
1#
#15750
0#
#15800
b1001101100000100 $
b11111111111111111001101100000100 !
b1001101100000100 '
b11111111111111111001101100000100 "
b11111111111111111001101100000100 (
b10011110 %
1#
#15850
0#
#15900
b110000111110111 $
b110000111110111 !
b110000111110111 '
b110000111110111 "
b110000111110111 (
b10011111 %
1#
#15950
0#
#16000
b11101101001 $
b11101101001 !
b11101101001 '
b11101101001 "
b11101101001 (
b10100000 %
1#
#16050
0#
#16100
b1011101010110100 $
b11111111111111111011101010110100 !
b1011101010110100 '
b11111111111111111011101010110100 "
b11111111111111111011101010110100 (
b10100001 %
1#
#16150
0#
#16200
b1000110110001000 $
b11111111111111111000110110001000 !
b1000110110001000 '
b11111111111111111000110110001000 "
b11111111111111111000110110001000 (
b10100010 %
1#
#16250
0#
#16300
b1101100100101000 $
b11111111111111111101100100101000 !
b1101100100101000 '
b11111111111111111101100100101000 "
b11111111111111111101100100101000 (
b10100011 %
1#
#16350
0#
#16400
b10000101101 $
b10000101101 !
b10000101101 '
b10000101101 "
b10000101101 (
b10100100 %
1#
#16450
0#
#16500
b11000011000111 $
b11000011000111 !
b11000011000111 '
b11000011000111 "
b11000011000111 (
b10100101 %
1#
#16550
0#
#16600
b1001110000101110 $
b11111111111111111001110000101110 !
b1001110000101110 '
b11111111111111111001110000101110 "
b11111111111111111001110000101110 (
b10100110 %
1#
#16650
0#
#16700
b1110010000001000 $
b11111111111111111110010000001000 !
b1110010000001000 '
b11111111111111111110010000001000 "
b11111111111111111110010000001000 (
b10100111 %
1#
#16750
0#
#16800
b100010100011100 $
b100010100011100 !
b100010100011100 '
b100010100011100 "
b100010100011100 (
b10101000 %
1#
#16850
0#
#16900
b1010011011111101 $
b11111111111111111010011011111101 !
b1010011011111101 '
b11111111111111111010011011111101 "
b11111111111111111010011011111101 (
b10101001 %
1#
#16950
0#
#17000
b11100101001 $
b11100101001 !
b11100101001 '
b11100101001 "
b11100101001 (
b10101010 %
1#
#17050
0#
#17100
b1001000000011100 $
b11111111111111111001000000011100 !
b1001000000011100 '
b11111111111111111001000000011100 "
b11111111111111111001000000011100 (
b10101011 %
1#
#17150
0#
#17200
b110011110000110 $
b110011110000110 !
b110011110000110 '
b110011110000110 "
b110011110000110 (
b10101100 %
1#
#17250
0#
#17300
b100011011010 $
b100011011010 !
b100011011010 '
b100011011010 "
b100011011010 (
b10101101 %
1#
#17350
0#
#17400
b1100011000111101 $
b11111111111111111100011000111101 !
b1100011000111101 '
b11111111111111111100011000111101 "
b11111111111111111100011000111101 (
b10101110 %
1#
#17450
0#
#17500
b1010011101100110 $
b11111111111111111010011101100110 !
b1010011101100110 '
b11111111111111111010011101100110 "
b11111111111111111010011101100110 (
b10101111 %
1#
#17550
0#
#17600
b1100010001110000 $
b11111111111111111100010001110000 !
b1100010001110000 '
b11111111111111111100010001110000 "
b11111111111111111100010001110000 (
b10110000 %
1#
#17650
0#
#17700
b10001110011 $
b10001110011 !
b10001110011 '
b10001110011 "
b10001110011 (
b10110001 %
1#
#17750
0#
#17800
b1001100110111010 $
b11111111111111111001100110111010 !
b1001100110111010 '
b11111111111111111001100110111010 "
b11111111111111111001100110111010 (
b10110010 %
1#
#17850
0#
#17900
b1011001101011110 $
b11111111111111111011001101011110 !
b1011001101011110 '
b11111111111111111011001101011110 "
b11111111111111111011001101011110 (
b10110011 %
1#
#17950
0#
#18000
b111100111111010 $
b111100111111010 !
b111100111111010 '
b111100111111010 "
b111100111111010 (
b10110100 %
1#
#18050
0#
#18100
b10111010101 $
b10111010101 !
b10111010101 '
b10111010101 "
b10111010101 (
b10110101 %
1#
#18150
0#
#18200
b1111011000011010 $
b11111111111111111111011000011010 !
b1111011000011010 '
b11111111111111111111011000011010 "
b11111111111111111111011000011010 (
b10110110 %
1#
#18250
0#
#18300
b10111001 $
b10111001 !
b10111001 '
b10111001 "
b10111001 (
b10110111 %
1#
#18350
0#
#18400
b110000100110111 $
b110000100110111 !
b110000100110111 '
b110000100110111 "
b110000100110111 (
b10111000 %
1#
#18450
0#
#18500
b11011110010110 $
b11011110010110 !
b11011110010110 '
b11011110010110 "
b11011110010110 (
b10111001 %
1#
#18550
0#
#18600
b10000111000000 $
b10000111000000 !
b10000111000000 '
b10000111000000 "
b10000111000000 (
b10111010 %
1#
#18650
0#
#18700
b1001111100100110 $
b11111111111111111001111100100110 !
b1001111100100110 '
b11111111111111111001111100100110 "
b11111111111111111001111100100110 (
b10111011 %
1#
#18750
0#
#18800
b1101010110110 $
b1101010110110 !
b1101010110110 '
b1101010110110 "
b1101010110110 (
b10111100 %
1#
#18850
0#
